keyring_proxy_socket/__init__.py
keyring_proxy_socket/_version.py
keyring_proxy_socket/py.typed
keyring_proxy_socket-0.1.19.4.dist-info/METADATA
keyring_proxy_socket-0.1.19.4.dist-info/WHEEL
keyring_proxy_socket-0.1.19.4.dist-info/entry_points.txt
keyring_proxy_socket-0.1.19.4.dist-info/RECORD
